chunin/__init__.py
chunin-0.0.1.dist-info/WHEEL
chunin-0.0.1.dist-info/METADATA
chunin-0.0.1.dist-info/RECORD
