Metadata-Version: 2.1
Name: chunin
Version: 0.0.1
Summary: Checks Union
Author: Oleh Mazur
Author-email: real.trolforever@gmail.com
Requires-Python: >=3.6,<4.0
Classifier: Programming Language :: Python :: 3
Classifier: Programming Language :: Python :: 3.6
Classifier: Programming Language :: Python :: 3.7
Classifier: Programming Language :: Python :: 3.8
Classifier: Programming Language :: Python :: 3.9
